Regalo
