Metadata-Version: 2.1
Name: Regalo
Version: 0.4.1
Summary: Creador de instaladores para windows
Home-page: https://github.com/nakato156/Regalo
Author: Nakato
Author-email: christianvelasces@gmail.com
License: MIT
Keywords: windows,installer,exe,executable,package
